README.rst
setup.cfg
setup.py
floodio/__init__.py
floodio/client.py
floodio/exc.py
floodio/floods.py
floodio/grids.py
floodio_python.egg-info/PKG-INFO
floodio_python.egg-info/SOURCES.txt
floodio_python.egg-info/dependency_links.txt
floodio_python.egg-info/pbr.json
floodio_python.egg-info/requires.txt
floodio_python.egg-info/top_level.txt