Metadata-Version: 1.0
Name: floodio-python
Version: 0.3
Summary: Flood.io client for Python 2 and 3
Home-page: https://github.com/EventMobi/floodio-python
Author: Devon Meunier
Author-email: devon@eventmobi.com
License: MIT
Platform: UNKNOWN
